{
  "sheet": "BannerBg",
  "defaultColumn": "Name",
  "definitions": [
    {
      "name": "Image",
      "converter": {
        "type": "icon"
      }
    },
    {
      "index": 1,
      "name": "Icon",
      "converter": {
        "type": "icon"
      }
    },
    {
      "index": 3,
      "name": "UnlockCondition",
      "converter": {
        "type": "link",
        "target": "BannerCondition"
      }
    },
    {
      "index": 7,
      "name": "SortKey"
    },
    {
      "index": 8,
      "name": "Name"
    }
  ]
}